meanas/LICENSE.md
meanas/README.md
meanas/__init__.py
meanas/eigensolvers.py
meanas/py.typed
meanas/fdfd/__init__.py
meanas/fdfd/bloch.py
meanas/fdfd/eme.py
meanas/fdfd/farfield.py
meanas/fdfd/functional.py
meanas/fdfd/operators.py
meanas/fdfd/scpml.py
meanas/fdfd/solvers.py
meanas/fdfd/waveguide_2d.py
meanas/fdfd/waveguide_3d.py
meanas/fdfd/waveguide_cyl.py
meanas/fdmath/__init__.py
meanas/fdmath/functional.py
meanas/fdmath/operators.py
meanas/fdmath/types.py
meanas/fdmath/vectorization.py
meanas/fdtd/__init__.py
meanas/fdtd/base.py
meanas/fdtd/boundaries.py
meanas/fdtd/energy.py
meanas/fdtd/misc.py
meanas/fdtd/pml.py
meanas/test/__init__.py
meanas/test/conftest.py
meanas/test/test_fdfd.py
meanas/test/test_fdfd_pml.py
meanas/test/test_fdtd.py
meanas/test/utils.py
meanas-0.10.dist-info/METADATA
meanas-0.10.dist-info/WHEEL
meanas-0.10.dist-info/licenses/LICENSE.md
meanas-0.10.dist-info/RECORD
