Metadata-Version: 2.4
Name: meanas
Version: 0.10
Summary: Electromagnetic simulation tools
Author-email: Jan Petykiewicz <jan@mpxd.net>
License: GNU Affero General Public License
License-File: LICENSE.md
Keywords: Bloch,EME,FDFD,FDTD,difference,electromagnetic,finite,mode,photonics,simulation,solver
Classifier: Development Status :: 4 - Beta
Classifier: Intended Audience :: Developers
Classifier: Intended Audience :: Science/Research
Classifier: License :: OSI Approved :: GNU Affero General Public License v3
Classifier: Programming Language :: Python :: 3
Classifier: Topic :: Scientific/Engineering :: Physics
Requires-Python: >=3.11
Requires-Dist: numpy>=2.0
Requires-Dist: scipy~=1.14
Provides-Extra: dev
Requires-Dist: gridlock; extra == 'dev'
Requires-Dist: pdoc; extra == 'dev'
Requires-Dist: pytest; extra == 'dev'
Provides-Extra: examples
Requires-Dist: gridlock>=2.0; extra == 'examples'
Provides-Extra: test
Requires-Dist: pytest; extra == 'test'
